ralisem/__init__.py
ralisem/base.py
ralisem/impls.py
ralisem-0.1.0.dist-info/LICENSE
ralisem-0.1.0.dist-info/WHEEL
ralisem-0.1.0.dist-info/METADATA
ralisem-0.1.0.dist-info/RECORD
