Metadata-Version: 2.1
Name: ralisem
Version: 0.1.0
Summary: Rate limit semaphore for async-style   (any core)
Home-page: https://github.com/deknowny/rate-limit-semaphore
License: MIT
Author: Yan Kurbatov
Author-email: deknowny@gmail.com
Requires-Python: >=3.7,<4.0
Classifier: License :: OSI Approved :: MIT License
Classifier: Programming Language :: Python :: 3
Classifier: Programming Language :: Python :: 3.10
Classifier: Programming Language :: Python :: 3.7
Classifier: Programming Language :: Python :: 3.8
Classifier: Programming Language :: Python :: 3.9
Provides-Extra: all
Provides-Extra: dev-all
Provides-Extra: dev-check
Provides-Extra: dev-deploy
Provides-Extra: dev-docs
Provides-Extra: dev-style
Provides-Extra: dev-test
Requires-Dist: anyio (>=3.5.0,<4.0.0)
Requires-Dist: autoflake (>=1.4,<2.0); extra == "dev-style" or extra == "dev-all"
Requires-Dist: black (>=21.11b1,<22.0); extra == "dev-style" or extra == "dev-all"
Requires-Dist: bumpversion (>=0.5.3,<0.6.0); extra == "dev-deploy" or extra == "dev-all"
Requires-Dist: coverage (>=6.1.2,<7.0.0); extra == "dev-test" or extra == "dev-all"
Requires-Dist: coveralls (>=3.3.1,<4.0.0); extra == "dev-test" or extra == "dev-all"
Requires-Dist: isort (>=5.10.1,<6.0.0); extra == "dev-style" or extra == "dev-all"
Requires-Dist: mike (>=1.1.2,<2.0.0); extra == "dev-docs" or extra == "dev-all"
Requires-Dist: mkdocs (>=1.2.3,<2.0.0); extra == "dev-docs" or extra == "dev-all"
Requires-Dist: mkdocs-material (>=8.0.2,<9.0.0); extra == "dev-docs" or extra == "dev-all"
Requires-Dist: mypy (>=0.930,<0.931); extra == "dev-check" or extra == "dev-all"
Requires-Dist: pre-commit (>=2.15.0,<3.0.0); extra == "dev-style" or extra == "dev-all"
Requires-Dist: pytest (>=6.2.5,<7.0.0); extra == "dev-test" or extra == "dev-all"
Requires-Dist: pytest-cov (>=3.0.0,<4.0.0); extra == "dev-test" or extra == "dev-all"
Project-URL: Documentation, https://deknowny.github.io/rate-limit-semaphore/latest/
